{"trial_id": "0122", "hyperparameters": {"space": [{"class_name": "Int", "config": {"name": "units", "default": null, "conditions": [], "min_value": 8, "max_value": 64, "step": 8, "sampling": "linear"}}, {"class_name": "Choice", "config": {"name": "learning_rate", "default": 0.01, "conditions": [], "values": [0.01, 0.001, 0.0001, 1e-05], "ordered": true}}, {"class_name": "Choice", "config": {"name": "activation", "default": "linear", "conditions": [], "values": ["linear", "relu"], "ordered": false}}, {"class_name": "Choice", "config": {"name": "batch_size", "default": 8, "conditions": [], "values": [8, 16, 32, 64], "ordered": true}}], "values": {"units": 32, "learning_rate": 1e-05, "activation": "linear", "batch_size": 32}}, "metrics": {"metrics": {"loss": {"direction": "min", "observations": [{"value": [7.392550468444824], "step": 182}]}, "mse": {"direction": "min", "observations": [{"value": [7.392550468444824], "step": 182}]}, "val_loss": {"direction": "min", "observations": [{"value": [10.471964836120605], "step": 182}]}, "val_mse": {"direction": "min", "observations": [{"value": [10.471964836120605], "step": 182}]}}}, "score": 10.471964836120605, "best_step": 182, "status": "COMPLETED", "message": null}